keyframe_scout/__init__.py
keyframe_scout/__main__.py
keyframe_scout/analyzer.py
keyframe_scout/azure_integration.py
keyframe_scout/batch.py
keyframe_scout/constants.py
keyframe_scout/extractor.py
keyframe_scout/selector.py
keyframe_scout/utils.py
keyframe_scout/vlm_utils.py
keyframe_scout-0.2.4.dist-info/licenses/LICENSE
keyframe_scout-0.2.4.dist-info/METADATA
keyframe_scout-0.2.4.dist-info/WHEEL
keyframe_scout-0.2.4.dist-info/entry_points.txt
keyframe_scout-0.2.4.dist-info/top_level.txt
keyframe_scout-0.2.4.dist-info/RECORD
