Metadata-Version: 2.4
Name: keyframe-scout
Version: 0.2.4
Summary: Intelligent video keyframe extraction for VLMs
Home-page: https://github.com/yourusername/keyframe-scout
Author: Jiajun Chen
Author-email: Jiajun Chen <cjj198909@gmail.com>
License-Expression: MIT
Project-URL: Homepage, https://github.com/yourusername/keyframe-scout
Project-URL: Issues, https://github.com/yourusername/keyframe-scout/issues
Keywords: video,keyframes,extraction,opencv,vlm,gpt4v
Classifier: Development Status :: 4 - Beta
Classifier: Intended Audience :: Developers
Classifier: Programming Language :: Python :: 3
Classifier: Programming Language :: Python :: 3.7
Classifier: Programming Language :: Python :: 3.8
Classifier: Programming Language :: Python :: 3.9
Classifier: Programming Language :: Python :: 3.10
Classifier: Programming Language :: Python :: 3.11
Classifier: Topic :: Multimedia :: Video
Requires-Python: >=3.7
License-File: LICENSE
Requires-Dist: opencv-python>=4.5.0
Requires-Dist: numpy>=1.19.0
Requires-Dist: Pillow>=8.0.0
Requires-Dist: tqdm>=4.50.0
Requires-Dist: scikit-image>=0.18.0
Provides-Extra: dev
Requires-Dist: pytest>=6.0; extra == "dev"
Requires-Dist: black>=21.0; extra == "dev"
Requires-Dist: twine>=3.0; extra == "dev"
Requires-Dist: wheel>=0.36; extra == "dev"
Provides-Extra: azure
Requires-Dist: openai>=1.0.0; extra == "azure"
Dynamic: author
Dynamic: home-page
Dynamic: license-file
Dynamic: requires-python
